{
  "annotation_type": "functional",
  "service_name": "",
  "service_category": "search",
  "operation_name": "",
  "capabilities": [
    "Flight comparison",
    "Search by multiple parameters (from, to, dates, adults, children, infants)",
    "Supports direct flights option"
  ],
  "input_parameters": [
    "from",
    "to",
    "outboundDate",
    "inboundDate",
    "adults",
    "children",
    "infants",
    "cabinClass",
    "directFlightsOnly"
  ],
  "output_parameters": [
    "offers",
    "cheapestPrice",
    "fastestDuration"
  ],
  "semantic_description": "Compares flight deals across multiple airlines based on user-specified parameters.",
  "keywords": [
    "flight comparison",
    "search by date",
    "airline search",
    "multi-parameter search"
  ],
  "required_inputs": [],
  "optional_inputs": [],
  "special_features": {
    "supports_multi_currency": true,
    "returns_cheapest_price": true,
    "returns_fastest_duration": true
  }
}